odoo/addons/mail_partner_opt_out/README.rst
odoo/addons/mail_partner_opt_out/__init__.py
odoo/addons/mail_partner_opt_out/__manifest__.py
odoo/addons/mail_partner_opt_out/i18n/it.po
odoo/addons/mail_partner_opt_out/i18n/mail_partner_opt_out.pot
odoo/addons/mail_partner_opt_out/models/__init__.py
odoo/addons/mail_partner_opt_out/models/mail_thread_blacklist.py
odoo/addons/mail_partner_opt_out/readme/CONTRIBUTORS.md
odoo/addons/mail_partner_opt_out/readme/DESCRIPTION.md
odoo/addons/mail_partner_opt_out/readme/USAGE.md
odoo/addons/mail_partner_opt_out/static/description/icon.png
odoo/addons/mail_partner_opt_out/static/description/index.html
odoo/addons/mail_partner_opt_out/tests/__init__.py
odoo/addons/mail_partner_opt_out/tests/test_mail_partner_opt_out.py
odoo/addons/mail_partner_opt_out/views/res_partner_views.xml
odoo_addon_mail_partner_opt_out-18.0.1.0.0.2.dist-info/METADATA
odoo_addon_mail_partner_opt_out-18.0.1.0.0.2.dist-info/WHEEL
odoo_addon_mail_partner_opt_out-18.0.1.0.0.2.dist-info/top_level.txt
odoo_addon_mail_partner_opt_out-18.0.1.0.0.2.dist-info/RECORD
